django_globals/__init__.py
django_globals/middleware.py
django_globals-0.3.2.dist-info/METADATA
django_globals-0.3.2.dist-info/RECORD
django_globals-0.3.2.dist-info/WHEEL
django_globals-0.3.2.dist-info/top_level.txt
